mini_control_arena/__init__.py
mini_control_arena/env.py
mini_control_arena/log_utils.py
mini_control_arena/runner.py
mini_control_arena/template.py
mini_control_arena-0.1.0rc6.dist-info/METADATA
mini_control_arena-0.1.0rc6.dist-info/WHEEL
mini_control_arena-0.1.0rc6.dist-info/entry_points.txt
mini_control_arena-0.1.0rc6.dist-info/top_level.txt
mini_control_arena-0.1.0rc6.dist-info/RECORD
