Metadata-Version: 2.4
Name: mini-control-arena
Version: 0.1.0rc6
Summary: A lightweight library for running AI Control experiments
Author-email: phys.w.s.lee@gmail.com
Requires-Python: >=3.12
Requires-Dist: click==8.2.1
Requires-Dist: datasets==4.0.0
Requires-Dist: inspect-ai==0.3.122
Requires-Dist: pydantic==2.11.7
Requires-Dist: openai==1.99.9
Requires-Dist: anthropic==0.66.0
Requires-Dist: mkdocs==1.6.1
Requires-Dist: mkdocs-material==9.5.45
Requires-Dist: mkdocstrings[python]==0.27.0
Requires-Dist: mkdocs-macros-plugin==1.3.9
